quecital/__init__.py
quecital/__main__.py
quecital/add_recital.py
quecital/multiline_recital_editor.py
quecital/multiline_text_editor.py
quecital/old_scratch.py
quecital/quecital.py
quecital/quiz.py
quecital/quiz_management.py
quecital/recital.py
quecital-1.4.0.dist-info/METADATA
quecital-1.4.0.dist-info/WHEEL
quecital-1.4.0.dist-info/entry_points.txt
quecital-1.4.0.dist-info/RECORD
