Metadata-Version: 2.1
Name: quecital
Version: 1.4.0
Summary: Fact quiz and line recital
Author: Robert Portelli
Author-email: github@robertportelli.com
Requires-Python: >=3.11
Classifier: Programming Language :: Python :: 3
Classifier: Programming Language :: Python :: 3.11
Classifier: Programming Language :: Python :: 3.12
Requires-Dist: click (>=8.1.7,<9.0.0)
Requires-Dist: prompt-toolkit (>=3.0.43,<4.0.0)
Requires-Dist: tomli-w (>=1.0.0,<2.0.0)
